truecolor/__init__.py
truecolor/colors.py
truecolor/functions.py
truecolor.py-0.0.2.dist-info/LICENSE
truecolor.py-0.0.2.dist-info/METADATA
truecolor.py-0.0.2.dist-info/WHEEL
truecolor.py-0.0.2.dist-info/top_level.txt
truecolor.py-0.0.2.dist-info/RECORD
