Metadata-Version: 2.1
Name: truecolor.py
Version: 0.0.2
Summary: A better console color library
Home-page: https://github.com/chanchan69/truecolor
Author: SirChanChan
Author-email: chanchan@sirchanchan.dev
License: UNKNOWN
Project-URL: Bug Tracker, https://github.com/chanchan69/truecolor/issues
Platform: UNKNOWN
Classifier: Programming Language :: Python :: 3
Classifier: License :: OSI Approved :: Apache Software License
Classifier: Operating System :: OS Independent
Requires-Python: >=3.1
License-File: LICENSE
